librestats/__init__.py
librestats/datasets.py
librestats-0.1.0.dist-info/licenses/LICENSE
librestats-0.1.0.dist-info/METADATA
librestats-0.1.0.dist-info/WHEEL
librestats-0.1.0.dist-info/top_level.txt
librestats-0.1.0.dist-info/RECORD
